datadictionary/__init__.py
datadictionary/config.py
datadictionary/profiler.py
datadictionary-0.0.6.dist-info/licenses/LICENSE
datadictionary-0.0.6.dist-info/METADATA
datadictionary-0.0.6.dist-info/WHEEL
datadictionary-0.0.6.dist-info/top_level.txt
datadictionary-0.0.6.dist-info/RECORD
