Metadata-Version: 2.4
Name: datadictionary
Version: 0.0.6
Summary: A package for profiling data and creating data dictionaries.
Home-page: https://github.com/jasonatwood/DataDictionary
Author: Jason Atwood
Author-email: jason@thedatatoldme.com
Project-URL: Bug Tracker, https://github.com/jasonatwood/DataDictionary/issues
Keywords: data dictionary,data profile,data profiler
Classifier: Programming Language :: Python :: 3
Classifier: License :: OSI Approved :: GNU General Public License v3 (GPLv3)
Classifier: Operating System :: OS Independent
Classifier: Development Status :: 5 - Production/Stable
Requires-Python: >=3.6
License-File: LICENSE
Requires-Dist: pandas>=1.0.0
Requires-Dist: openpyxl
Dynamic: license-file
